pygame_matplotlib/__init__.py
pygame_matplotlib/backend_pygame.py
pygame_matplotlib/gui_window.py
pygame_matplotlib-0.5.dist-info/METADATA
pygame_matplotlib-0.5.dist-info/WHEEL
pygame_matplotlib-0.5.dist-info/entry_points.txt
pygame_matplotlib-0.5.dist-info/licenses/LICENSE
pygame_matplotlib-0.5.dist-info/RECORD
