Metadata-Version: 2.4
Name: pygame-matplotlib
Version: 0.5
Summary: A matplotlib backend using pygame.
Project-URL: Homepage, https://github.com/lionel42/pygame-matplotlib-backend
Project-URL: Repository, https://github.com/lionel42/pygame-matplotlib-backend
Author: Lionel42
License-File: LICENSE
Keywords: backend,matplotlib,plot,pygame
Classifier: Development Status :: 5 - Production/Stable
Classifier: License :: OSI Approved :: MIT License
Classifier: Operating System :: OS Independent
Classifier: Programming Language :: Python :: 3
Requires-Python: >=3.9
Requires-Dist: matplotlib
Requires-Dist: pygame-gui
